ci_release_publisher/__init__.py
ci_release_publisher/__main__.py
ci_release_publisher/__version__.py
ci_release_publisher/config.py
ci_release_publisher/enum.py
ci_release_publisher/env.py
ci_release_publisher/exception.py
ci_release_publisher/github.py
ci_release_publisher/latest_release.py
ci_release_publisher/numbered_release.py
ci_release_publisher/requests_retry.py
ci_release_publisher/tag_release.py
ci_release_publisher/temporary_store_release.py
ci_release_publisher/travis.py
ci_release_publisher-0.3.0.dist-info/LICENSE
ci_release_publisher-0.3.0.dist-info/METADATA
ci_release_publisher-0.3.0.dist-info/WHEEL
ci_release_publisher-0.3.0.dist-info/entry_points.txt
ci_release_publisher-0.3.0.dist-info/top_level.txt
ci_release_publisher-0.3.0.dist-info/RECORD
