Metadata-Version: 2.1
Name: ci-release-publisher
Version: 0.3.0
Summary: A script for publishing Travis-CI build artifacts on GitHub Releases
Home-page: https://github.com/nurupo/ci-release-publisher
Author: Maxim Biro
Author-email: nurupo.contributions@gmail.com
License: MIT
Platform: UNKNOWN
Classifier: Development Status :: 3 - Alpha
Classifier: Intended Audience :: Developers
Classifier: Topic :: Software Development
Classifier: Environment :: Console
Classifier: Natural Language :: English
Classifier: License :: OSI Approved :: MIT License
Classifier: Programming Language :: Python :: 3
Classifier: Programming Language :: Python :: 3.5
Classifier: Programming Language :: Python :: 3.6
Classifier: Programming Language :: Python :: 3.7
Classifier: Programming Language :: Python :: Implementation :: CPython
Requires-Python: >=3.5
Requires-Dist: PyGithub (>=1.42)
Requires-Dist: requests (>=2.20.0)
